Metadata-Version: 2.1
Name: mumodule
Version: 0.0.1.0.0.1
Summary: A short summary about your package
Author: Álvaro Navarro
Author-email: alvaro.nl@ua.es
License: MIT
Platform: UNKNOWN
Classifier: License :: OSI Approved :: MIT License
Classifier: Programming Language :: Python :: 3
Classifier: Operating System :: Microsoft :: Windows :: Windows 10
Classifier: Development Status :: 5 - Production/Stable
Classifier: Intended Audience :: Education
License-File: LICENSE.txt
